Workbook

Sheet Configuracion
A1: PARAMETROS DE COSTOS - IMPRESION 3D (BAMBU LAB A1)
A3: Materiales (precio por rollo de 1 kg)
A4: Material | B4: Precio rollo ($)
A5: PLA Pro | B5: 279 | C5: <- agrega mas materiales aqui (PETG, ABS, TPU...)
A6: PLA Matte | B6: 289
A10: Parametros generales
A11: Peso del rollo (g) | B11: 1000
A12: Costo electricidad ($/kWh) | B12: 2.8
A13: Consumo promedio A1 (kW) | B13: 0.1
A14: Desgaste impresora por hora ($) | B14: 6
A15: Mano de obra por hora ($) | B15: 180
A16: Empaque basico ($) | B16: 8
A17: Tasa de fallos / desperdicio (%) | B17: 0.05
A18: Margen de ganancia (%) | B18: 0.4
A19: Comision Mercado Libre (%) | B19: 0.16
A20: Redondeo de precio final (multiplo de $) | B20: 10

Sheet Cotizador
A1: COTIZADOR DE IMPRESION 3D
A3: Datos de la pieza
A4: Nombre del modelo
A5: Material | B5: PLA Pro
A6: Peso pieza (g) | B6: 50
A7: Purga AMS (g) | B7: 5
A8: Horas de impresion | B8: 3
A9: Minutos de postproceso | B9: 10
A10: Cantidad | B10: 1
A11: Plataforma de venta | B11: Venta directa
A13: Costos unitarios
A14: Precio rollo del material ($) | B14: =IFERROR(INDEX(Configuracion!$B$5:$B$8,MATCH(B5,Configuracion!$A$5:$A$8,0)),0)
A15: Costo material unitario | B15: =(B6+B7)*B14/Configuracion!$B$11
A16: Electricidad unitaria | B16: =B8*Configuracion!$B$13*Configuracion!$B$12
A17: Desgaste unitario | B17: =B8*Configuracion!$B$14
A18: Mano de obra unitaria | B18: =(B9/60)*Configuracion!$B$15
A19: Subtotal antes de fallos | B19: =SUM(B15:B18)
A20: Ajuste por tasa de fallos | B20: =B19*Configuracion!$B$17
A21: Empaque unitario | B21: =Configuracion!$B$16
A22: Costo total unitario | B22: =B19+B20+B21
A24: Precio de venta
A25: Precio sugerido unitario (venta directa) | B25: =B22*(1+Configuracion!$B$18)
A26: Precio unitario en Mercado Libre | B26: =B25/(1-Configuracion!$B$19)
A27: Precio final unitario (segun plataforma) | B27: =IF(B11="Mercado Libre",B26,B25)
A28: Precio final redondeado | B28: =CEILING(B27,Configuracion!$B$20)
A29: Ganancia unitaria estimada | B29: =B28-B22
A31: Totales del pedido (x Cantidad)
A32: Costo total del pedido | B32: =B22*B10
A33: Precio total del pedido | B33: =B28*B10
A34: Ganancia total estimada | B34: =B33-B32

Sheet Historial
A1: Fecha | B1: Modelo | C1: Cliente | D1: Cantidad | E1: Costo | F1: Venta | G1: Ganancia
G2: =IF(F2="","",F2-E2)
G3: =IF(F3="","",F3-E3)
G4: =IF(F4="","",F4-E4)
G5: =IF(F5="","",F5-E5)
G6: =IF(F6="","",F6-E6)
G7: =IF(F7="","",F7-E7)
G8: =IF(F8="","",F8-E8)
G9: =IF(F9="","",F9-E9)
G10: =IF(F10="","",F10-E10)
G11: =IF(F11="","",F11-E11)
G12: =IF(F12="","",F12-E12)
G13: =IF(F13="","",F13-E13)
... G51: =IF(F51="","",F51-E51)
